{
    "69": {
        "nom": "ABRAN Grégory",
        "adresse": "40, bd Victor Hugo 06000 Nice",
        "telephone": "T . 06 15 33 07 26",
        "email": "abran.gregory@gmail.com"
    },
    "416": {
        "nom": "ACHACHE Hélène",
        "adresse": "1, rue Alberti 06000 Nice",
        "telephone": "T . 04 93 82 14 14",
        "email": "hhlnhh@aol.com"
    },
    "286": {
        "nom": "ADAD Eric",
        "adresse": "57, Promenade des Anglais 06000 Nice",
        "telephone": "T . 04 92 10 03 47",
        "email": "eadad@talliance-avocats.fr"
    },
    "548": {
        "nom": "AGAEV Alexandre",
        "adresse": "15, rue Massena 06000 Nice",
        "telephone": "T . 04 93 80 02 01",
        "email": "j.a.avocat.nice@gmail.com"
    },
    "93": {
        "nom": "AGNETTI Eric",
        "adresse": "18, rue Pastorelli 06000 Nice",
        "telephone": "T . 04 93 53 54 55",
        "email": "eric.agnetti@wanadoo.fr"
    },
    "093": {
        "nom": "AGNETTI Laura",
        "adresse": "18, rue Pastorelli 06000 Nice",
        "telephone": "T . 04 93 53 54 55",
        "email": "laura.agnetti.avocat@gmail.com"
    },
    "62": {
        "nom": "AGOSTI Pascal",
        "adresse": "CAPRIOLI ET ASSOCIES (Selarl) 9, Avenue Henri Matisse 06200 Nice",
        "telephone": "T . 04.93.83.31.31",
        "email": "contact@caprioli-avocats.com"
    },
    "134": {
        "nom": "AH-TOY Sylvia",
        "adresse": "65-67, bd Gambetta Résidence les Provinces de France 06000 Nice",
        "telephone": "T . 06 62 81 67 93",
        "email": "sylvia.ah-toy@wanadoo.fr"
    }
}